mpiptop.py
mpiptop-0.2.0.dist-info/licenses/LICENSE
mpiptop-0.2.0.dist-info/METADATA
mpiptop-0.2.0.dist-info/WHEEL
mpiptop-0.2.0.dist-info/entry_points.txt
mpiptop-0.2.0.dist-info/top_level.txt
mpiptop-0.2.0.dist-info/RECORD
