Metadata-Version: 2.4
Name: mpiptop
Version: 0.2.0
Summary: TUI for viewing MPI Python stacks across hosts
Author: yieldthought
License-Expression: MIT
Project-URL: Homepage, https://github.com/yieldthought/mpiptop
Project-URL: Repository, https://github.com/yieldthought/mpiptop
Keywords: mpi,tui,py-spy,distributed,debugging
Classifier: Programming Language :: Python :: 3
Classifier: Operating System :: POSIX :: Linux
Requires-Python: >=3.8
License-File: LICENSE
Requires-Dist: rich>=13.7
Requires-Dist: py-spy>=0.4.1
Dynamic: license-file
